README.md
setup.py
ixconfig/__init__.py
ixconfig/__main__.py
ixconfig/core.py
ixconfig/util.py
ixconfig.egg-info/PKG-INFO
ixconfig.egg-info/SOURCES.txt
ixconfig.egg-info/dependency_links.txt
ixconfig.egg-info/entry_points.txt
ixconfig.egg-info/requires.txt
ixconfig.egg-info/top_level.txt