Metadata-Version: 2.1
Name: ixconfig
Version: 0.1.1
Summary: UNKNOWN
Home-page: https://github.com/beasteers/ixconfig
Author: Bea Steers
Author-email: bea.steers@gmail.com
License: MIT License
Platform: UNKNOWN
